complex_numbers/__init__.py
complex_numbers/complex_number.py
complexviz-0.1.dist-info/DESCRIPTION.rst
complexviz-0.1.dist-info/METADATA
complexviz-0.1.dist-info/RECORD
complexviz-0.1.dist-info/WHEEL
complexviz-0.1.dist-info/metadata.json
complexviz-0.1.dist-info/top_level.txt
