Metadata-Version: 2.0
Name: complexviz
Version: 0.1
Summary: Python package for visualization of complex numbers
Home-page: https://github.com/soumendra/complexviz
Author: Jay Trivedi
Author-email: mail.jaytrivedi@gmail.com
License: UNKNOWN
Platform: UNKNOWN
